Perceptron/__init__.py
Perceptron/perceptron.py
logger/__init__.py
Perceptrone_viral3899-1.1.1.dist-info/LICENSE
Perceptrone_viral3899-1.1.1.dist-info/METADATA
Perceptrone_viral3899-1.1.1.dist-info/WHEEL
Perceptrone_viral3899-1.1.1.dist-info/top_level.txt
Perceptrone_viral3899-1.1.1.dist-info/RECORD
